basicplaycard/BasicPlayingCard.py
basicplaycard/__init__.py
basicplaycard-0.0.2.dist-info/LICENSE
basicplaycard-0.0.2.dist-info/METADATA
basicplaycard-0.0.2.dist-info/WHEEL
basicplaycard-0.0.2.dist-info/top_level.txt
basicplaycard-0.0.2.dist-info/RECORD
